{
  "main": {
    "id": "1e88e0c835e08205",
    "type": "split",
    "children": [
      {
        "id": "f91477cc6b83bcfc",
        "type": "tabs",
        "children": [
          {
            "id": "5e999be4314cc14f",
            "type": "leaf",
            "state": {
              "type": "markdown",
              "state": {
                "file": "CALENDARIOS/01-calendario-platino/R1/2024-07-01-MATCH1.md",
                "mode": "source",
                "source": false
              },
              "icon": "lucide-file",
              "title": "2024-07-01-MATCH1"
            }
          }
        ]
      }
    ],
    "direction": "vertical"
  },
  "left": {
    "id": "6ca039392f8512aa",
    "type": "split",
    "children": [
      {
        "id": "a32448e8eb7638b5",
        "type": "tabs",
        "children": [
          {
            "id": "2f57040bc95983a3",
            "type": "leaf",
            "state": {
              "type": "file-explorer",
              "state": {
                "sortOrder": "alphabetical"
              },
              "icon": "lucide-folder-closed",
              "title": "Explorador de archivos"
            }
          },
          {
            "id": "7938ca62c6e84ec1",
            "type": "leaf",
            "state": {
              "type": "search",
              "state": {
                "query": "",
                "matchingCase": false,
                "explainSearch": false,
                "collapseAll": false,
                "extraContext": false,
                "sortOrder": "alphabetical"
              },
              "icon": "lucide-search",
              "title": "Buscar"
            }
          },
          {
            "id": "46e1541cf667b81d",
            "type": "leaf",
            "state": {
              "type": "bookmarks",
              "state": {},
              "icon": "lucide-bookmark",
              "title": "Bookmarks"
            }
          }
        ]
      }
    ],
    "direction": "horizontal",
    "width": 300
  },
  "right": {
    "id": "97d3351bc71b06ec",
    "type": "split",
    "children": [
      {
        "id": "6a1586eff5953311",
        "type": "tabs",
        "children": [
          {
            "id": "6cfee2eb1eb4b442",
            "type": "leaf",
            "state": {
              "type": "backlink",
              "state": {
                "collapseAll": false,
                "extraContext": false,
                "sortOrder": "alphabetical",
                "showSearch": false,
                "searchQuery": "",
                "backlinkCollapsed": false,
                "unlinkedCollapsed": true
              },
              "icon": "links-coming-in",
              "title": "Backlinks"
            }
          },
          {
            "id": "4eb3931d9a33db32",
            "type": "leaf",
            "state": {
              "type": "outgoing-link",
              "state": {
                "linksCollapsed": false,
                "unlinkedCollapsed": true
              },
              "icon": "links-going-out",
              "title": "Outgoing links"
            }
          },
          {
            "id": "928959e7483bf456",
            "type": "leaf",
            "state": {
              "type": "tag",
              "state": {
                "sortOrder": "frequency",
                "useHierarchy": true
              },
              "icon": "lucide-tags",
              "title": "Tags"
            }
          },
          {
            "id": "022f57de71927e54",
            "type": "leaf",
            "state": {
              "type": "outline",
              "state": {},
              "icon": "lucide-list",
              "title": "Outline"
            }
          }
        ]
      }
    ],
    "direction": "horizontal",
    "width": 300,
    "collapsed": true
  },
  "left-ribbon": {
    "hiddenItems": {
      "switcher:Abrir selector rápido": false,
      "graph:Abrir vista gráfica": false,
      "canvas:Crear nuevo lienzo": false,
      "daily-notes:Abrir la nota de hoy": false,
      "templates:Insertar plantilla": false,
      "command-palette:Abrir paleta de comandos": false
    }
  },
  "active": "5e999be4314cc14f",
  "lastOpenFiles": [
    "CALENDARIOS/02-calendario-oro/R10/2024-07-01-MATCH1.md",
    "CALENDARIOS/02-calendario-oro/R10/2024-07-01-MATCH2.md",
    "CALENDARIOS/02-calendario-oro/R10/2024-07-01-MATCH3.md",
    "CALENDARIOS/02-calendario-oro/R10/2024-07-01-MATCH4.md",
    "CALENDARIOS/02-calendario-oro/R10/2024-07-01-MATCH5.md",
    "CALENDARIOS/02-calendario-oro/R11/2024-07-01-MATCH1.md",
    "CALENDARIOS/02-calendario-oro/R11/2024-07-01-MATCH2.md",
    "CALENDARIOS/02-calendario-oro/R11/2024-07-01-MATCH3.md",
    "CALENDARIOS/02-calendario-oro/R11/2024-07-01-MATCH4.md",
    "CALENDARIOS/02-calendario-oro/R11/2024-07-01-MATCH5.md",
    "CALENDARIOS/02-calendario-oro/R10",
    "CALENDARIOS/02-calendario-oro/R11",
    "Sin título 1.canvas",
    "CALENDARIOS/01-calendario-platino/R1/2024-07-01-MATCH1.md",
    "CALENDARIOS/01-calendario-platino/R11/2024-07-01-MATCH5.md",
    "CALENDARIOS/01-calendario-platino/R11/2024-07-01-MATCH4.md",
    "CALENDARIOS/01-calendario-platino/R11/2024-07-01-MATCH3.md",
    "CALENDARIOS/01-calendario-platino/R11/2024-07-01-MATCH2.md",
    "CALENDARIOS/01-calendario-platino/R11/2024-07-01-MATCH1.md",
    "CALENDARIOS/01-calendario-platino/R10/2024-07-01-MATCH5.md",
    "CALENDARIOS/01-calendario-platino/R10/2024-07-01-MATCH4.md",
    "CALENDARIOS/01-calendario-platino/R10/2024-07-01-MATCH3.md",
    "CALENDARIOS/01-calendario-platino/R10/2024-07-01-MATCH2.md",
    "CALENDARIOS/01-calendario-platino/R10/2024-07-01-MATCH1.md",
    "CALENDARIOS/01-calendario-platino/R9/2024-07-01-MATCH1.md",
    "CALENDARIOS/01-calendario-platino/R11",
    "CALENDARIOS/01-calendario-platino/R9 - copia/2024-07-01-MATCH5.md",
    "CALENDARIOS/01-calendario-platino/R9 - copia/2024-07-01-MATCH4.md",
    "CALENDARIOS/01-calendario-platino/R9 - copia/2024-07-01-MATCH3.md",
    "CALENDARIOS/01-calendario-platino/R9 - copia/2024-07-01-MATCH2.md",
    "CALENDARIOS/01-calendario-platino/R9 - copia",
    "CALENDARIOS/01-calendario-platino/R10",
    "MVP/ARCHIVO",
    "MVP/NORTE",
    "MVP/Nueva carpeta",
    "MVP/RAGNAROK/AEP",
    "MVP/RAGNAROK",
    "Sin título.canvas",
    "Sin título 6.canvas",
    "Sin título 5.canvas",
    "Sin título 4.canvas",
    "Sin título 3.canvas",
    "Sin título 2.canvas"
  ]
}